{"xxe.v1.users.get":{"method":"GET","url":"http://localhost:3000/xxeapis/v1/users","body":"{\n\"term\":{\n  \"name\":\"works\",\n  \"slug\":\"1231\"\n},\n\"parent\":29,\n\"description\":\"works\",\n\"title\":\"1。2111\",\n\"name\":\"term1\",\n\"author\":1,\n\"postType\":\"attachment\",\n\"content\":\"test 1。2\",\n\"contentFiltered\":true,\n\"password\":\"1。2\",\n\"displayName\":\"222x\",\n\"wp_capabilities\":[\"editor\",\"author\"],\n\"_wp_attached_file\":\"1111\"\n}\n","overrideMimeType":false,"headers":[["Content-Type","application/json"]]},"xxe.v1.user.login":{"method":"POST","url":"http://localhost:3000/xxeapis/v1/user/login","body":"{\n\"login\":\"root\",\n\"pass\":\"123456\"\n}\n","overrideMimeType":false,"headers":[["Content-Type","application/json"]]},"xxe.v1.user.logout":{"method":"GET","url":"http://localhost:3000/xxeapis/v1/user/logout","body":"{\n\"login\":\"root\",\n\"pass\":\"123456\"\n}\n","overrideMimeType":false,"headers":[["Content-Type","application/json"]]},"xxe.v1.users.post":{"method":"POST","url":"http://localhost:3000/xxeapis/v1/users","body":"{\n\"login\":\"root1\",\n\"pass\":\"123456\",\n\"nicename\":\"root1\",\n\"email\":\"36081189@qq.com\",\n\"url\":\"/uploads/1.jpg\",\n\"status\":1,\n\"displayName\":\"管理员1\"\n}\n","overrideMimeType":false,"headers":[["Content-Type","application/json"]]},"xxe.v1.users.delete":{"method":"DELETE","url":"http://localhost:3000/xxeapis/v1/users/9","body":"{\n\"term\":{\n  \"name\":\"works\",\n  \"slug\":\"1231\"\n},\n\"parent\":29,\n\"description\":\"works\",\n\"title\":\"1。2111\",\n\"name\":\"term1\",\n\"author\":1,\n\"postType\":\"attachment\",\n\"content\":\"test 1。2\",\n\"contentFiltered\":true,\n\"password\":\"1。2\",\n\"displayName\":\"222x\",\n\"wp_capabilities\":[\"editor\",\"author\"],\n\"_wp_attached_file\":\"1111\"\n}\n","overrideMimeType":false,"headers":[["Content-Type","application/json"]]},"xxe.v1.users.query":{"method":"GET","url":"http://localhost:3000/xxeapis/v1/users/page=0;order=createdAt-","body":"{\n\"term\":{\n  \"name\":\"works\",\n  \"slug\":\"1231\"\n},\n\"parent\":29,\n\"description\":\"works\",\n\"title\":\"1。2111\",\n\"name\":\"term1\",\n\"author\":1,\n\"postType\":\"attachment\",\n\"content\":\"test 1。2\",\n\"contentFiltered\":true,\n\"password\":\"1。2\",\n\"displayName\":\"222x\",\n\"wp_capabilities\":[\"editor\",\"author\"],\n\"_wp_attached_file\":\"1111\"\n}\n","overrideMimeType":false,"headers":[["Content-Type","application/json"]]},"xxe.v1.devices.query":{"method":"GET","url":"http://localhost:3000/xxeapis/v1/devices/page=0;order=createdAt-","body":"\n","overrideMimeType":false,"headers":[["Content-Type","application/json"]]},"xxe.v1.devices.post":{"method":"POST","url":"http://localhost:3000/xxeapis/v1/devices","body":"{\n\"uuid\": \"11111112\",\n\"parent\": \"\",\n\"base\": {\n\"base1\":\"base1\",\n\"base2\":\"base2\"\n},\n\"extend\": {\n\"latitude\":11.1,\n\"longitude\":22.2\n}\n}","overrideMimeType":false,"headers":[["Content-Type","application/json"]]},"xxe.v1.userdevices.get":{"method":"GET","url":"http://localhost:3000/xxeapis/v1/userdevices","body":"","overrideMimeType":false,"headers":[["Content-Type","application/json"]]},"xxe.v1.userdevices.post":{"method":"POST","url":"http://localhost:3000/xxeapis/v1/userdevices","body":"{\n\"userId\":1,\n\"deviceId\":1\n}","overrideMimeType":false,"headers":[["Content-Type","application/json"]]},"xxe.v1.userdevices.unbind":{"method":"POST","url":"http://localhost:3000/xxeapis/v1/userdevices/unbind","body":"{\n\"userId\":1,\n\"deviceId\":1\n}","overrideMimeType":false,"headers":[["Content-Type","application/json"]]},"xxe.v1.userdevices.bind":{"method":"POST","url":"http://localhost:3000/xxeapis/v1/userdevices/bind","body":"{\n\"userId\":1,\n\"deviceId\":1\n}","overrideMimeType":false,"headers":[["Content-Type","application/json"]]},"xxe.v1.firmwares.get":{"method":"GET","url":"http://localhost:3000/xxeapis/v1/firmwares","body":"","overrideMimeType":false,"headers":[["Content-Type","application/json"]]},"xxe.v1.firmwares.post":{"method":"POST","url":"http://localhost:3000/xxeapis/v1/firmwares","body":"{\n\"name\":\"v.1.bin\",\n\"path\":\"v.1.MD5SUM.SIZE.bin\"\n}","overrideMimeType":false,"headers":[["Content-Type","application/json"]]},"xxe.v1.firmwares.delete":{"method":"DELETE","url":"http://localhost:3000/xxeapis/v1/firmwares/3","body":"","overrideMimeType":false,"headers":[["Content-Type","application/json"]]},"xxe.v1.cmds.get":{"method":"GET","url":"http://localhost:3000/xxeapis/v1/cmds","body":"","overrideMimeType":false,"headers":[["Content-Type","application/json"]]},"xxe.v1.cmds.post":{"method":"POST","url":"http://localhost:3000/xxeapis/v1/cmds","body":"{\n\"uuid\":\"11111111\",\n\"name\":\"update\",\n\"content\":{\"name\":\"1.bin\"},\n\"status\":\"init\"\n}","overrideMimeType":false,"headers":[["Content-Type","application/json"]]},"xxe.v1.cmds.delete":{"method":"DELETE","url":"http://localhost:3000/xxeapis/v1/cmds/2","body":"{\n\"uuid\":\"11111111\",\n\"name\":\"update\",\n\"content\":{\"name\":\"1.bin\"},\n\"status\":\"init\"\n}","overrideMimeType":false,"headers":[["Content-Type","application/json"]]},"xxe.v1.cmds.query":{"method":"GET","url":"http://localhost:3000/xxeapis/v1/cmds/order=createdAt-","body":"","overrideMimeType":false,"headers":[["Content-Type","application/json"]]},"xxe.v1.datas.get":{"method":"GET","url":"http://localhost:3000/xxeapis/v1/datas","body":"","overrideMimeType":false,"headers":[["Content-Type","application/json"]]},"xxe.v1.datas.post":{"method":"POST","url":"http://localhost:3000/xxeapis/v1/datas","body":"{\n\"uuid\":\"11111111\",\n\"key\":\"hum\",\n\"value\":23.2\n}","overrideMimeType":false,"headers":[["Content-Type","application/json"]]},"xxe.v1.datas.delete":{"method":"DELETE","url":"http://localhost:3000/xxeapis/v1/datas/14","body":"{\n\"uuid\":\"11111111\",\n\"key\":\"hum\",\n\"value\":23.2\n}","overrideMimeType":false,"headers":[["Content-Type","application/json"]]},"xxe.v1.datas.query":{"method":"GET","url":"http://localhost:3000/xxeapis/v1/datas/uuid=22222222;order=createdAt-","body":"{\n\"uuid\":\"22222222\",\n\"key\":\"temp\",\n\"value\":23.2\n}","overrideMimeType":false,"headers":[["Content-Type","application/json"]]}}